prompt_writing_assistant/__init__.py
prompt_writing_assistant/database.py
prompt_writing_assistant/designer.py
prompt_writing_assistant/file_manager.py
prompt_writing_assistant/log.py
prompt_writing_assistant/prompt_helper.py
prompt_writing_assistant/utils.py
prompt_writing_assistant/code_helper/coder.py
prompt_writing_assistant/server/__main__.py
prompt_writing_assistant/server/models.py
prompt_writing_assistant/server/mcp/__init__.py
prompt_writing_assistant/server/mcp/content.py
prompt_writing_assistant/server/mcp/math.py
prompt_writing_assistant/server/mcp/resource.py
prompt_writing_assistant/server/mcp/weather.py
prompt_writing_assistant/server/router/recommended.py
prompt_writing_assistant-0.3.7.dist-info/METADATA
prompt_writing_assistant-0.3.7.dist-info/WHEEL
prompt_writing_assistant-0.3.7.dist-info/top_level.txt
prompt_writing_assistant-0.3.7.dist-info/RECORD
